airflow_ci/__init__.py
airflow_ci/airflow.py
airflow_ci/airflow.pyi
airflow_ci/api/__init__.py
airflow_ci/api/config.py
airflow_ci/api/main.py
airflow_ci/const.py
airflow_ci/pipeline.py
airflow_ci/task.py
airflow_ci/webhook/__init__.py
airflow_ci/webhook/attrs.py
airflow_ci/webhook/gitea.py
airflow_ci-0.0.5.dist-info/METADATA
airflow_ci-0.0.5.dist-info/WHEEL
airflow_ci-0.0.5.dist-info/LICENSE
airflow_ci-0.0.5.dist-info/RECORD
