Metadata-Version: 2.1
Name: airflow-ci
Version: 0.0.5
Summary: ci tool using airflow
License: MIT
Author: phi.friday
Author-email: phi.friday@gmail.com
Requires-Python: >=3.10,<4.0
Classifier: Development Status :: 1 - Planning
Classifier: Intended Audience :: Developers
Classifier: License :: OSI Approved :: MIT License
Classifier: Operating System :: OS Independent
Classifier: Programming Language :: Python :: 3
Classifier: Programming Language :: Python :: 3.10
Classifier: Programming Language :: Python :: 3.11
Classifier: Programming Language :: Python :: 3
Classifier: Programming Language :: Python :: 3.10
Requires-Dist: fastapi (>=0.91.0,<0.92.0)
Requires-Dist: gitpython (>=3.1.30,<4.0.0)
Requires-Dist: httpx (>=0.23.3,<0.24.0)
Requires-Dist: orjson (>=3.8.6,<4.0.0)
Requires-Dist: pydantic[email] (>=1.10.4,<2.0.0)
Requires-Dist: pyyaml (>=6.0,<7.0)
Requires-Dist: requests (>=2.28.2,<3.0.0)
Requires-Dist: toml (>=0.10.2,<0.11.0)
